emacs_bindings.py
emacs_keys_everywhere-0.2.dist-info/DESCRIPTION.rst
emacs_keys_everywhere-0.2.dist-info/METADATA
emacs_keys_everywhere-0.2.dist-info/RECORD
emacs_keys_everywhere-0.2.dist-info/WHEEL
emacs_keys_everywhere-0.2.dist-info/entry_points.txt
emacs_keys_everywhere-0.2.dist-info/metadata.json
emacs_keys_everywhere-0.2.dist-info/top_level.txt
