Metadata-Version: 2.0
Name: emacs-keys-everywhere
Version: 0.2
Summary: Enable Emacs style key bindings on the desktop.
Home-page: https://github.com/rahiel/emacs-keys-everywhere
Author: Rahiel Kasim
Author-email: rahielkasim@gmail.com
License: GPLv3+
Keywords: emacs key bindings keybindings
Platform: UNKNOWN
Classifier: Development Status :: 4 - Beta
Classifier: Environment :: Console
Classifier: Intended Audience :: End Users/Desktop
Classifier: License :: OSI Approved :: GNU General Public License v3 or later (GPLv3+)
Classifier: Operating System :: POSIX
Classifier: Programming Language :: Python :: 3
Classifier: Topic :: Utilities
